juan.py
juan-0.1.0.dist-info/entry_points.txt
juan-0.1.0.dist-info/LICENSE.md
juan-0.1.0.dist-info/WHEEL
juan-0.1.0.dist-info/METADATA
juan-0.1.0.dist-info/RECORD
